[{
            "title": "How to Choose an Arizona Loan Officer: Market Selection Guide \u0026 NMLS Verification",
            "date": "January 29, 2025",
            "categories": null,
            "excerpt": null,
            "image": "https://images.unsplash.com/photo-1504384308090-c894fdcc538d?auto=format\u0026fit=crop\u0026w=1200\u0026q=80",
            "permalink": "http://localhost:1406/blogs/how-to-choose-an-arizona-loan-officer-market-selection-guide-nmls-verification/",
            "tags": null
        },{
            "title": "Arizona NMLS Licensing Guide: What You Need to Know About Loan Officer Credentials",
            "date": "January 28, 2025",
            "categories": null,
            "excerpt": null,
            "image": "https://images.unsplash.com/photo-1454165804606-c3d57bc86b40?auto=format\u0026fit=crop\u0026w=1200\u0026q=80",
            "permalink": "http://localhost:1406/blogs/arizona-nmls-licensing-guide-what-you-need-to-know-about-loan-officer-credentials/",
            "tags": null
        },{
            "title": "Arizona Jumbo \u0026 Portfolio Loan Officers: Flexible Underwriting for Complex Income \u0026 High-Net-Worth Borrowers",
            "date": "January 27, 2025",
            "categories": null,
            "excerpt": null,
            "image": "https://images.unsplash.com/photo-1507679799987-c73779587ccf?auto=format\u0026fit=crop\u0026w=1200\u0026q=80",
            "permalink": "http://localhost:1406/blogs/arizona-jumbo-portfolio-loan-officers-flexible-underwriting-for-complex-income-high-net-worth-borrowers/",
            "tags": null
        },{
            "title": "New Construction \u0026 Builder Loan Officers in Arizona: Navigating Chandler \u0026 Scottsdale Builder Programs",
            "date": "January 26, 2025",
            "categories": null,
            "excerpt": null,
            "image": "https://images.unsplash.com/photo-1501183638710-841dd1904471?auto=format\u0026fit=crop\u0026w=1200\u0026q=80",
            "permalink": "http://localhost:1406/blogs/new-construction-builder-loan-officers-in-arizona-navigating-chandler-scottsdale-builder-programs/",
            "tags": null
        }]
