[{
            "title": "Choosing a Wyoming Loan Officer: Broker vs Bank vs Credit Union MLO",
            "date": "January 22, 2024",
            "categories": null,
            "excerpt": null,
            "image": "https://images.unsplash.com/photo-1556761175-b413da4baf72?auto=format\u0026fit=crop\u0026w=2000\u0026q=80",
            "permalink": "http://localhost:1383/blogs/choosing-a-wyoming-loan-officer-broker-vs-bank-vs-credit-union-mlo/",
            "tags": ["wyoming loan officers","broker vs bank","loan officer selection","mortgage professional comparison"]
        },{
            "title": "Wholesale Pricing in Wyoming: How Brokers Beat Bank Rates by 0.25%–0.375%",
            "date": "January 19, 2024",
            "categories": null,
            "excerpt": null,
            "image": "https://images.unsplash.com/photo-1460925895917-afdab827c52f?auto=format\u0026fit=crop\u0026w=2000\u0026q=80",
            "permalink": "http://localhost:1383/blogs/wholesale-pricing-in-wyoming-how-brokers-beat-bank-rates-by-0.250.375/",
            "tags": ["wholesale pricing","wyoming mortgage brokers","retail vs wholesale","broker advantage"]
        },{
            "title": "Wyoming Loan Officer Licensing: NMLS Requirements and Verification",
            "date": "January 16, 2024",
            "categories": null,
            "excerpt": null,
            "image": "https://images.unsplash.com/photo-1450101499163-c8848c66ca85?auto=format\u0026fit=crop\u0026w=2000\u0026q=80",
            "permalink": "http://localhost:1383/blogs/wyoming-loan-officer-licensing-nmls-requirements-and-verification/",
            "tags": ["wyoming loan officers","NMLS licensing","mortgage regulation","consumer protection"]
        }]
